LICENSE.txt
README.md
pyproject.toml
setup.cfg
setup.py
verify_types/__init__.py
verify_types/decorators.py
verify_types/exceptions.py
verify_types.egg-info/PKG-INFO
verify_types.egg-info/SOURCES.txt
verify_types.egg-info/dependency_links.txt
verify_types.egg-info/not-zip-safe
verify_types.egg-info/top_level.txt