Metadata-Version: 2.1
Name: verify-types
Version: 1.0.5
Summary: Lib to verify types of functions
Home-page: https://gitlab.com/victorhdcoelho/verify-types/
Author: Victor Coelho
Author-email: victorhdcoelho@gmail.com
License: UNKNOWN
Platform: UNKNOWN
Classifier: Programming Language :: Python :: 3
Classifier: License :: OSI Approved :: MIT License
Classifier: Operating System :: OS Independent
Requires-Python: >=3.6
